FileUtils/__init__.py
FileUtils/counter.py
FileUtils/paths.py
Merkurial_FileUtils-0.0.0.dist-info/LICENSE
Merkurial_FileUtils-0.0.0.dist-info/METADATA
Merkurial_FileUtils-0.0.0.dist-info/WHEEL
Merkurial_FileUtils-0.0.0.dist-info/top_level.txt
Merkurial_FileUtils-0.0.0.dist-info/RECORD
